apex_legends_api/__init__.py
apex_legends_api/al_api.py
apex_legends_api/al_base.py
apex_legends_api/al_domain.py
apex_legends_api-2.0.3.dist-info/LICENSE
apex_legends_api-2.0.3.dist-info/METADATA
apex_legends_api-2.0.3.dist-info/WHEEL
apex_legends_api-2.0.3.dist-info/top_level.txt
apex_legends_api-2.0.3.dist-info/RECORD
