Metadata-Version: 2.1
Name: apex-legends-api
Version: 2.0.3
Summary: Python wrapper for https://apexlegendsapi.com
Home-page: https://github.com/johnsturgeon/apex-legends-api
Author: John Sturgeon
Author-email: john.sturgeon@me.com
License: MIT
Platform: UNKNOWN
Requires-Python: >=3.9.*
Requires-Dist: requests (==2.25.1)
Requires-Dist: arrow (==1.0.3)
Requires-Dist: Python-Deprecated (==1.1.0)
